#ifndef BYTECODE_H
#define BYTECODE_H

#define opc_nop 0 	
#define opc_aconst_null 1 	
#define opc_iconst_m1 2 	
#define opc_iconst_0 3 	
#define opc_iconst_1 4 	
#define opc_iconst_2 5 	
#define opc_iconst_3 6 	
#define opc_iconst_4 7 	
#define opc_iconst_5 8 	
#define opc_lconst_0 9 	
#define opc_lconst_1 10 	
#define opc_fconst_0 11 	
#define opc_fconst_1 12 	
#define opc_fconst_2 13 	
#define opc_dconst_0 14 	
#define opc_dconst_1 15 	
#define opc_bipush 16 	
#define opc_sipush 17 	
#define opc_ldc 18 	
#define opc_ldc_w 19 	
#define opc_ldc2_w 20 	
#define opc_iload 21 	
#define opc_lload 22 	
#define opc_fload 23 	
#define opc_dload 24 	
#define opc_aload 25 	
#define opc_iload_0 26 	
#define opc_iload_1 27 	
#define opc_iload_2 28 	
#define opc_iload_3 29 	
#define opc_lload_0 30 	
#define opc_lload_1 31 	
#define opc_lload_2 32 	
#define opc_lload_3 33 	
#define opc_fload_0 34 	
#define opc_fload_1 35 	
#define opc_fload_2 36 	
#define opc_fload_3 37 	
#define opc_dload_0 38 	
#define opc_dload_1 39 	
#define opc_dload_2 40 	
#define opc_dload_3 41 	
#define opc_aload_0 42 	
#define opc_aload_1 43 	
#define opc_aload_2 44 	
#define opc_aload_3 45 	
#define opc_iaload 46 	
#define opc_laload 47 	
#define opc_faload 48 	
#define opc_daload 49 	
#define opc_aaload 50 	
#define opc_baload 51 	
#define opc_caload 52 	
#define opc_saload 53 	
#define opc_istore 54 	
#define opc_lstore 55 	
#define opc_fstore 56 	
#define opc_dstore 57 	
#define opc_astore 58 	
#define opc_istore_0 59 	
#define opc_istore_1 60 	
#define opc_istore_2 61 	
#define opc_istore_3 62 	
#define opc_lstore_0 63 	
#define opc_lstore_1 64 	
#define opc_lstore_2 65 	
#define opc_lstore_3 66 	
#define opc_fstore_0 67 	
#define opc_fstore_1 68 	
#define opc_fstore_2 69 	
#define opc_fstore_3 70 	
#define opc_dstore_0 71 	
#define opc_dstore_1 72 	
#define opc_dstore_2 73 	
#define opc_dstore_3 74 	
#define opc_astore_0 75 	
#define opc_astore_1 76 	
#define opc_astore_2 77 	
#define opc_astore_3 78 	
#define opc_iastore 79 	
#define opc_lastore 80 	
#define opc_fastore 81 	
#define opc_dastore 82 	
#define opc_aastore 83 	
#define opc_bastore 84 	
#define opc_castore 85 	
#define opc_sastore 86 	
#define opc_pop 87 	
#define opc_pop2 88 	
#define opc_dup 89 	
#define opc_dup_x1 90 	
#define opc_dup_x2 91 	
#define opc_dup2 92 	
#define opc_dup2_x1 93 	
#define opc_dup2_x2 94 	
#define opc_swap 95 	
#define opc_iadd 96 	
#define opc_ladd 97 	
#define opc_fadd 98 	
#define opc_dadd 99 	
#define opc_isub 100 	
#define opc_lsub 101 	
#define opc_fsub 102 	
#define opc_dsub 103 	
#define opc_imul 104 	
#define opc_lmul 105 	
#define opc_fmul 106 	
#define opc_dmul 107 	
#define opc_idiv 108 	
#define opc_ldiv 109 	
#define opc_fdiv 110 	
#define opc_ddiv 111 	
#define opc_irem 112 	
#define opc_lrem 113 	
#define opc_frem 114 	
#define opc_drem 115 	
#define opc_ineg 116 	
#define opc_lneg 117 	
#define opc_fneg 118 	
#define opc_dneg 119 	
#define opc_ishl 120 	
#define opc_lshl 121 	
#define opc_ishr 122 	
#define opc_lshr 123 	
#define opc_iushr 124 	
#define opc_lushr 125 	
#define opc_iand 126 	
#define opc_land 127 	
#define opc_ior 128 	
#define opc_lor 129 	
#define opc_ixor 130 	
#define opc_lxor 131 	
#define opc_iinc 132 	
#define opc_i2l 133 	
#define opc_i2f 134 	
#define opc_i2d 135 	
#define opc_l2i 136 	
#define opc_l2f 137 	
#define opc_l2d 138 	
#define opc_f2i 139 	
#define opc_f2l 140 	
#define opc_f2d 141 	
#define opc_d2i 142 	
#define opc_d2l 143 	
#define opc_d2f 144 	
#define opc_i2b 145 	
#define opc_i2c 146 	
#define opc_i2s 147 	
#define opc_lcmp 148 	
#define opc_fcmpl 149 	
#define opc_fcmpg 150 	
#define opc_dcmpl 151 	
#define opc_dcmpg 152 	
#define opc_ifeq 153 	
#define opc_ifne 154 	
#define opc_iflt 155 	
#define opc_ifge 156 	
#define opc_ifgt 157 	
#define opc_ifle 158 	
#define opc_if_icmpeq 159 	
#define opc_if_icmpne 160 	
#define opc_if_icmplt 161 	
#define opc_if_icmpge 162 	
#define opc_if_icmpgt 163 	
#define opc_if_icmple 164 	
#define opc_if_acmpeq 165 	
#define opc_if_acmpne 166 	
#define opc_goto 167 	
#define opc_jsr 168 	
#define opc_ret 169 	
#define opc_tableswitch 170 	
#define opc_lookupswitch 171 	
#define opc_ireturn 172 	
#define opc_lreturn 173 	
#define opc_freturn 174 	
#define opc_dreturn 175 	
#define opc_areturn 176 	
#define opc_return 177 	
#define opc_getstatic 178 	
#define opc_putstatic 179 	
#define opc_getfield 180 	
#define opc_putfield 181 	
#define opc_invokevirtual 182 	
#define opc_invokespecial 183 	
#define opc_invokestatic 184 	
#define opc_invokeinterface 185 	
#define opc_invokedynamic 186 	
#define opc_new 187 	
#define opc_newarray 188 	
#define opc_anewarray 189 	
#define opc_arraylength 190 	
#define opc_athrow 191 	
#define opc_checkcast 192 	
#define opc_instanceof 193 	
#define opc_monitorenter 194 	
#define opc_monitorexit 195 	
#define opc_wide 196 	
#define opc_multianewarray 197 	
#define opc_ifnull 198 	
#define opc_ifnonnull 199 	
#define opc_goto_w 200 	
#define opc_jsr_w 201 	
#define opc_breakpoint 202 	
#define opc_impdep1 254 	
#define opc_impdep2 	 255 	


#include "classfile.h"
typedef enum { 
    OP_NONE, OP_CP, OP_LOCAL, OP_LITERAL, OP_BRANCH, OP_SPECIAL 
} OpType;

typedef struct {
  const char* name;
  int operands;
  OpType type;
} opcode_info;

extern const opcode_info opcode_table[256];

#endif
