[0] = { "nop", 0, OP_NONE },
[1] = { "aconst_null", 0, OP_NONE },
[2] = { "iconst_m1", 0, OP_NONE },
[3] = { "iconst_0", 0, OP_NONE },
[4] = { "iconst_1", 0, OP_NONE },
[5] = { "iconst_2", 0, OP_NONE },
[6] = { "iconst_3", 0, OP_NONE },
[7] = { "iconst_4", 0, OP_NONE },
[8] = { "iconst_5", 0, OP_NONE },
[9] = { "lconst_0", 0, OP_NONE },
[10] = { "lconst_1", 0, OP_NONE },
[11] = { "fconst_0", 0, OP_NONE },
[12] = { "fconst_1", 0, OP_NONE },
[13] = { "fconst_2", 0, OP_NONE },
[14] = { "dconst_0", 0, OP_NONE },
[15] = { "dconst_1", 0, OP_NONE },
[16] = { "bipush", 1, OP_LITERAL },
[17] = { "sipush", 2, OP_LITERAL },
[18] = { "ldc", 1, OP_CP },
[19] = { "ldc_w", 2, OP_CP },
[20] = { "ldc2_w", 2, OP_CP },
[21] = { "iload", 1, OP_LOCAL },
[22] = { "lload", 1, OP_LOCAL },
[23] = { "fload", 1, OP_LOCAL },
[24] = { "dload", 1, OP_LOCAL },
[25] = { "aload", 1, OP_LOCAL },
[26] = { "iload_0", 0, OP_NONE },
[27] = { "iload_1", 0, OP_NONE },
[28] = { "iload_2", 0, OP_NONE },
[29] = { "iload_3", 0, OP_NONE },
[30] = { "lload_0", 0, OP_NONE },
[31] = { "lload_1", 0, OP_NONE },
[32] = { "lload_2", 0, OP_NONE },
[33] = { "lload_3", 0, OP_NONE },
[34] = { "fload_0", 0, OP_NONE },
[35] = { "fload_1", 0, OP_NONE },
[36] = { "fload_2", 0, OP_NONE },
[37] = { "fload_3", 0, OP_NONE },
[38] = { "dload_0", 0, OP_NONE },
[39] = { "dload_1", 0, OP_NONE },
[40] = { "dload_2", 0, OP_NONE },
[41] = { "dload_3", 0, OP_NONE },
[42] = { "aload_0", 0, OP_NONE },
[43] = { "aload_1", 0, OP_NONE },
[44] = { "aload_2", 0, OP_NONE },
[45] = { "aload_3", 0, OP_NONE },
[46] = { "iaload", 0, OP_NONE },
[47] = { "laload", 0, OP_NONE },
[48] = { "faload", 0, OP_NONE },
[49] = { "daload", 0, OP_NONE },
[50] = { "aaload", 0, OP_NONE },
[51] = { "baload", 0, OP_NONE },
[52] = { "caload", 0, OP_NONE },
[53] = { "saload", 0, OP_NONE },
[54] = { "istore", 1, OP_LOCAL },
[55] = { "lstore", 1, OP_LOCAL },
[56] = { "fstore", 1, OP_LOCAL },
[57] = { "dstore", 1, OP_LOCAL },
[58] = { "astore", 1, OP_LOCAL },
[59] = { "istore_0", 0, OP_NONE },
[60] = { "istore_1", 0, OP_NONE },
[61] = { "istore_2", 0, OP_NONE },
[62] = { "istore_3", 0, OP_NONE },
[63] = { "lstore_0", 0, OP_NONE },
[64] = { "lstore_1", 0, OP_NONE },
[65] = { "lstore_2", 0, OP_NONE },
[66] = { "lstore_3", 0, OP_NONE },
[67] = { "fstore_0", 0, OP_NONE },
[68] = { "fstore_1", 0, OP_NONE },
[69] = { "fstore_2", 0, OP_NONE },
[70] = { "fstore_3", 0, OP_NONE },
[71] = { "dstore_0", 0, OP_NONE },
[72] = { "dstore_1", 0, OP_NONE },
[73] = { "dstore_2", 0, OP_NONE },
[74] = { "dstore_3", 0, OP_NONE },
[75] = { "astore_0", 0, OP_NONE },
[76] = { "astore_1", 0, OP_NONE },
[77] = { "astore_2", 0, OP_NONE },
[78] = { "astore_3", 0, OP_NONE },
[79] = { "iastore", 0, OP_NONE },
[80] = { "lastore", 0, OP_NONE },
[81] = { "fastore", 0, OP_NONE },
[82] = { "dastore", 0, OP_NONE },
[83] = { "aastore", 0, OP_NONE },
[84] = { "bastore", 0, OP_NONE },
[85] = { "castore", 0, OP_NONE },
[86] = { "sastore", 0, OP_NONE },
[87] = { "pop", 0, OP_NONE },
[88] = { "pop2", 0, OP_NONE },
[89] = { "dup", 0, OP_NONE },
[90] = { "dup_x1", 0, OP_NONE },
[91] = { "dup_x2", 0, OP_NONE },
[92] = { "dup2", 0, OP_NONE },
[93] = { "dup2_x1", 0, OP_NONE },
[94] = { "dup2_x2", 0, OP_NONE },
[95] = { "swap", 0, OP_NONE },
[96] = { "iadd", 0, OP_NONE },
[97] = { "ladd", 0, OP_NONE },
[98] = { "fadd", 0, OP_NONE },
[99] = { "dadd", 0, OP_NONE },
[100] = { "isub", 0, OP_NONE },
[101] = { "lsub", 0, OP_NONE },
[102] = { "fsub", 0, OP_NONE },
[103] = { "dsub", 0, OP_NONE },
[104] = { "imul", 0, OP_NONE },
[105] = { "lmul", 0, OP_NONE },
[106] = { "fmul", 0, OP_NONE },
[107] = { "dmul", 0, OP_NONE },
[108] = { "idiv", 0, OP_NONE },
[109] = { "ldiv", 0, OP_NONE },
[110] = { "fdiv", 0, OP_NONE },
[111] = { "ddiv", 0, OP_NONE },
[112] = { "irem", 0, OP_NONE },
[113] = { "lrem", 0, OP_NONE },
[114] = { "frem", 0, OP_NONE },
[115] = { "drem", 0, OP_NONE },
[116] = { "ineg", 0, OP_NONE },
[117] = { "lneg", 0, OP_NONE },
[118] = { "fneg", 0, OP_NONE },
[119] = { "dneg", 0, OP_NONE },
[120] = { "ishl", 0, OP_NONE },
[121] = { "lshl", 0, OP_NONE },
[122] = { "ishr", 0, OP_NONE },
[123] = { "lshr", 0, OP_NONE },
[124] = { "iushr", 0, OP_NONE },
[125] = { "lushr", 0, OP_NONE },
[126] = { "iand", 0, OP_NONE },
[127] = { "land", 0, OP_NONE },
[128] = { "ior", 0, OP_NONE },
[129] = { "lor", 0, OP_NONE },
[130] = { "ixor", 0, OP_NONE },
[131] = { "lxor", 0, OP_NONE },
[132] = { "iinc", 2, OP_SPECIAL },
[133] = { "i2l", 0, OP_NONE },
[134] = { "i2f", 0, OP_NONE },
[135] = { "i2d", 0, OP_NONE },
[136] = { "l2i", 0, OP_NONE },
[137] = { "l2f", 0, OP_NONE },
[138] = { "l2d", 0, OP_NONE },
[139] = { "f2i", 0, OP_NONE },
[140] = { "f2l", 0, OP_NONE },
[141] = { "f2d", 0, OP_NONE },
[142] = { "d2i", 0, OP_NONE },
[143] = { "d2l", 0, OP_NONE },
[144] = { "d2f", 0, OP_NONE },
[145] = { "i2b", 0, OP_NONE },
[146] = { "i2c", 0, OP_NONE },
[147] = { "i2s", 0, OP_NONE },
[148] = { "lcmp", 0, OP_NONE },
[149] = { "fcmpl", 0, OP_NONE },
[150] = { "fcmpg", 0, OP_NONE },
[151] = { "dcmpl", 0, OP_NONE },
[152] = { "dcmpg", 0, OP_NONE },
[153] = { "ifeq", 2, OP_BRANCH },
[154] = { "ifne", 2, OP_BRANCH },
[155] = { "iflt", 2, OP_BRANCH },
[156] = { "ifge", 2, OP_BRANCH },
[157] = { "ifgt", 2, OP_BRANCH },
[158] = { "ifle", 2, OP_BRANCH },
[159] = { "if_icmpeq", 2, OP_BRANCH },
[160] = { "if_icmpne", 2, OP_BRANCH },
[161] = { "if_icmplt", 2, OP_BRANCH },
[162] = { "if_icmpge", 2, OP_BRANCH },
[163] = { "if_icmpgt", 2, OP_BRANCH },
[164] = { "if_icmple", 2, OP_BRANCH },
[165] = { "if_acmpeq", 2, OP_BRANCH },
[166] = { "if_acmpne", 2, OP_BRANCH },
[167] = { "goto", 2, OP_BRANCH },
[168] = { "jsr", 2, OP_BRANCH },
[169] = { "ret", 1, OP_LOCAL },
[170] = { "tableswitch", -1, OP_SPECIAL },
[171] = { "lookupswitch", -1, OP_SPECIAL },
[172] = { "ireturn", 0, OP_NONE },
[173] = { "lreturn", 0, OP_NONE },
[174] = { "freturn", 0, OP_NONE },
[175] = { "dreturn", 0, OP_NONE },
[176] = { "areturn", 0, OP_NONE },
[177] = { "return", 0, OP_NONE },
[178] = { "getstatic", 2, OP_CP },
[179] = { "putstatic", 2, OP_CP },
[180] = { "getfield", 2, OP_CP },
[181] = { "putfield", 2, OP_CP },
[182] = { "invokevirtual", 2, OP_CP },
[183] = { "invokespecial", 2, OP_CP },
[184] = { "invokestatic", 2, OP_CP },
[185] = { "invokeinterface", 4, OP_SPECIAL },
[186] = { "invokedynamic", 4, OP_SPECIAL },
[187] = { "new", 2, OP_CP },
[188] = { "newarray", 1, OP_LITERAL },
[189] = { "anewarray", 2, OP_CP },
[190] = { "arraylength", 0, OP_NONE },
[191] = { "athrow", 0, OP_NONE },
[192] = { "checkcast", 2, OP_CP },
[193] = { "instanceof", 2, OP_CP },
[194] = { "monitorenter", 0, OP_NONE },
[195] = { "monitorexit", 0, OP_NONE },
[196] = { "wide", -1, OP_SPECIAL },
[197] = { "multianewarray", 3, OP_SPECIAL },
[198] = { "ifnull", 2, OP_BRANCH },
[199] = { "ifnonnull", 2, OP_BRANCH },
[200] = { "goto_w", 4, OP_BRANCH },
[201] = { "jsr_w", 4, OP_BRANCH },
[202] = { "breakpoint", 0, OP_NONE },
[254] = { "impdep1", 0, OP_NONE },
[255] = { "impdep2", 0, OP_NONE }
